Metadata-Version: 2.1
Name: temppathlib
Version: 1.2.0
Summary: Wrap tempfile to give you pathlib.Path.
Home-page: https://github.com/Parquery/temppathlib
Author: Marko Ristin
Author-email: marko@parquery.com
License: UNKNOWN
Keywords: tempfile pathlib temporary file directory mkdtemp mkstemp
Platform: UNKNOWN
Classifier: Development Status :: 5 - Production/Stable
Classifier: Intended Audience :: Developers
Classifier: License :: OSI Approved :: MIT License
Classifier: Programming Language :: Python :: 3.6
Classifier: Programming Language :: Python :: 3.7
Classifier: Programming Language :: Python :: 3.8
Classifier: Programming Language :: Python :: 3.9
Classifier: Programming Language :: Python :: 3.10
Provides-Extra: dev
License-File: LICENSE.txt
